[
  {
    "Name": "Нарушение авторских прав",
    "Description": "Полка, файл или группа нарушают авторские права"
  },
  {
    "Name": "Порнография",
    "Description": "Полка, файл или группа содержат материалы порнографического характера"
  },
  {
    "Name": "Призывы к насилию",
    "Description": "Полка, файл или группа содержат материалы, пропагандирующие насилие или жестокость"
  },
  {
    "Name": "Экстремизм и терроризм",
    "Description": "Полка, файл или группа содержат материалы экстремистского или террористического характера"
  },
  {
    "Name": "Разжигание ненависти",
    "Description": "Полка, файл или группа содержат материалы, разжигающие ненависть по признаку расы, национальности, религии или другим признакам"
  },
  {
    "Name": "Мошенничество и обман",
    "Description": "Полка, файл или группа содержат материалы, связанные с мошенничеством, фейковыми схемами или обманом пользователей"
  },
  {
    "Name": "Пропаганда наркотиков",
    "Description": "Полка, файл или группа содержат информацию о производстве, продаже или употреблении наркотических веществ"
  },
  {
    "Name": "Распространение вредоносного ПО",
    "Description": "Полка, файл или группа содержат вирусы, трояны или иное вредоносное программное обеспечение"
  },
  {
    "Name": "Незаконные материалы",
    "Description": "Полка, файл или группа содержат информацию, нарушающую законы и законодательные нормы"
  },
  {
    "Name": "Личные и конфиденциальные данные",
    "Description": "Полка, файл или группа содержат персональные или конфиденциальные данные без согласия их владельца"
  },
  {
    "Name": "Другое",
    "Description": "Полка, файл или группа содержат иную информацию нарушающую действующее законодательство"
  }
]
